x12_utils/__init__.py
x12_utils/x12_generator.py
x12_utils/x12_validator.py
x12_utils-0.3.0.dist-info/WHEEL
x12_utils-0.3.0.dist-info/METADATA
x12_utils-0.3.0.dist-info/RECORD
