Metadata-Version: 2.1
Name: x12-utils
Version: 0.3.0
Summary: Lightweight utilities for working with x12 EDI
Home-page: https://github.com/willingham/x12-utils
License: MIT
Author: willingham
Author-email: thomas@tshows.us
Requires-Python: >=3.7,<4.0
Classifier: License :: OSI Approved :: MIT License
Classifier: Programming Language :: Python :: 3
Classifier: Programming Language :: Python :: 3.7
Requires-Dist: pyx12 (>=2.3,<3.0)
Project-URL: Repository, https://github.com/willingham/x12-utils
